persist_cache/__init__.py
persist_cache/caching.py
persist_cache/helpers.py
persist_cache/persist_cache.py
persist_cache/pickle.py
persist_cache/py.typed
persist_cache/serialization.py
persist_cache-0.4.4.dist-info/METADATA
persist_cache-0.4.4.dist-info/WHEEL
persist_cache-0.4.4.dist-info/licenses/LICENCE
persist_cache-0.4.4.dist-info/RECORD
