Metadata-Version: 2.4
Name: persist-cache
Version: 0.4.4
Summary: An easy-to-use Python library for lightning-fast persistent function caching.
Project-URL: Homepage, https://github.com/umarbutler/persist-cache
Project-URL: Documentation, https://github.com/umarbutler/persist-cache/blob/main/README.md
Project-URL: Issues, https://github.com/umarbutler/persist-cache/issues
Project-URL: Source, https://github.com/umarbutler/persist-cache
Author-email: Umar Butler <umar@umar.au>
License: MIT
License-File: LICENCE
Keywords: cache,caching,decorator,function,functions,local,memoisation,memoise,memoization,memoize,optimisation,optimise,optimising,optimization,optimize,optimizing,performance,persistent,speed
Classifier: Development Status :: 4 - Beta
Classifier: Intended Audience :: Developers
Classifier: Intended Audience :: Information Technology
Classifier: License :: OSI Approved :: MIT License
Classifier: Operating System :: OS Independent
Classifier: Programming Language :: Python :: 3.9
Classifier: Programming Language :: Python :: 3.10
Classifier: Programming Language :: Python :: 3.11
Classifier: Programming Language :: Python :: 3.12
Classifier: Programming Language :: Python :: 3.13
Classifier: Programming Language :: Python :: Implementation :: CPython
Classifier: Topic :: Software Development :: Libraries :: Python Modules
Classifier: Topic :: Utilities
Classifier: Typing :: Typed
Requires-Python: >=3.9
Requires-Dist: dill>=0.3.7
Requires-Dist: filelock>=3.13.1
Requires-Dist: msgspec>=0.18.6
Requires-Dist: xxhash>=3.4.1
